rockhopper-0.2.0.dist-info/top_level.txt
rockhopper-0.2.0.dist-info/entry_points.txt
rockhopper-0.2.0.dist-info/WHEEL
rockhopper-0.2.0.dist-info/LICENSE
rockhopper-0.2.0.dist-info/METADATA
rockhopper-0.2.0.dist-info/RECORD
rockhopper/hook-rockhopper.py
rockhopper/_ragged_array.py
rockhopper/_version.py
rockhopper/__init__.py
rockhopper/_slugs/ragged_array-Linux-64bit.so
rockhopper/_slugs/ragged_array.json
