Metadata-Version: 2.1
Name: rockhopper
Version: 0.2.0
Summary: Ragged (rows with different lengths) 2D NumPy arrays.
Home-page: https://github.com/bwoodsend/rockhopper
Author: Brénainn Woodsend
Author-email: bwoodsend@gmail.com
License: MIT license
Keywords: rockhopper
Classifier: Intended Audience :: Developers
Classifier: License :: OSI Approved :: MIT License
Classifier: Natural Language :: English
Classifier: Programming Language :: Python :: 3
Classifier: Programming Language :: Python :: 3.6
Classifier: Programming Language :: Python :: 3.7
Classifier: Programming Language :: Python :: 3.8
Classifier: Programming Language :: Python :: 3.9
Classifier: Programming Language :: Python :: 3.10
Requires-Python: >=3.6
License-File: LICENSE
Requires-Dist: cslug
Requires-Dist: numpy (>=1.16.0)
Provides-Extra: test
Requires-Dist: pytest (>=3) ; extra == 'test'
Requires-Dist: pytest-order ; extra == 'test'
Requires-Dist: coverage ; extra == 'test'
Requires-Dist: pytest-cov ; extra == 'test'
Requires-Dist: coverage-conditional-plugin ; extra == 'test'
Requires-Dist: hypothesis ; extra == 'test'
